[
    {
        "id": "ACM",
        "name": "Red Hat Advanced Cluster Management",
        "repo": null,
        "website": null,
        "domain": null,
        "language": null,
        "ecosystem": "RedHat",
        "project_tag": "RedHat-ACM",
        "issue_count": 2126
    },
    {
        "id": "TRACING",
        "name": null,
        "repo": null,
        "website": null,
        "domain": null,
        "language": null,
        "ecosystem": "RedHat",
        "project_tag": "RedHat-TRACING",
        "issue_count": 1882
    },
    {
        "id": "JBWS",
        "name": null,
        "repo": null,
        "website": null,
        "domain": null,
        "language": null,
        "ecosystem": "RedHat",
        "project_tag": "RedHat-JBWS",
        "issue_count": 3948
    },
    {
        "id": "CRW",
        "name": null,
        "repo": null,
        "website": null,
        "domain": null,
        "language": null,
        "ecosystem": "RedHat",
        "project_tag": "RedHat-CRW",
        "issue_count": 3070
    },
    {
        "id": "MULTIARCH",
        "name": null,
        "repo": null,
        "website": null,
        "domain": null,
        "language": null,
        "ecosystem": "RedHat",
        "project_tag": "RedHat-MULTIARCH",
        "issue_count": 2109
    },
    {
        "id": "TEIIDDES",
        "name": null,
        "repo": null,
        "website": null,
        "domain": null,
        "language": null,
        "ecosystem": "RedHat",
        "project_tag": "RedHat-TEIIDDES",
        "issue_count": 3099
    },
    {
        "id": "RHBPMS",
        "name": null,
        "repo": null,
        "website": null,
        "domain": null,
        "language": null,
        "ecosystem": "RedHat",
        "project_tag": "RedHat-RHBPMS",
        "issue_count": 4026
    },
    {
        "name": "WildFly Elytron",
        "id": "WFCORE",
        "repo": "https://github.com/wildfly-security",
        "website": "http://wildfly.org",
        "domain": "Middleware",
        "language": null,
        "ecosystem": "RedHat",
        "project_tag": "RedHat-WFCORE",
        "issue_count": 5469
    },
    {
        "id": "UNDERTOW",
        "name": null,
        "repo": null,
        "website": null,
        "domain": null,
        "language": null,
        "ecosystem": "RedHat",
        "project_tag": "RedHat-UNDERTOW",
        "issue_count": 1989
    },
    {
        "id": "ERRAI",
        "name": null,
        "repo": null,
        "website": null,
        "domain": null,
        "language": null,
        "ecosystem": "RedHat",
        "project_tag": "RedHat-ERRAI",
        "issue_count": 1104
    },
    {
        "id": "OADP",
        "name": null,
        "repo": null,
        "website": null,
        "domain": null,
        "language": null,
        "ecosystem": "RedHat",
        "project_tag": "RedHat-OADP",
        "issue_count": 1002
    },
    {
        "id": "RHDEVDOCS",
        "name": null,
        "repo": null,
        "website": null,
        "domain": null,
        "language": null,
        "ecosystem": "RedHat",
        "project_tag": "RedHat-RHDEVDOCS",
        "issue_count": 3540
    },
    {
        "id": "MAISTRA",
        "name": null,
        "repo": null,
        "website": null,
        "domain": null,
        "language": null,
        "ecosystem": "RedHat",
        "project_tag": "RedHat-MAISTRA",
        "issue_count": 2215
    },
    {
        "id": "ODC",
        "name": null,
        "repo": null,
        "website": null,
        "domain": null,
        "language": null,
        "ecosystem": "RedHat",
        "project_tag": "RedHat-ODC",
        "issue_count": 1998
    },
    {
        "id": "HAC",
        "name": null,
        "repo": null,
        "website": null,
        "domain": null,
        "language": null,
        "ecosystem": "RedHat",
        "project_tag": "RedHat-HAC",
        "issue_count": 3012
    },
    {
        "id": "MGDCTRS",
        "name": null,
        "repo": null,
        "website": null,
        "domain": null,
        "language": null,
        "ecosystem": "RedHat",
        "project_tag": "RedHat-MGDCTRS",
        "issue_count": 1273
    },
    {
        "id": "HAL",
        "name": null,
        "repo": null,
        "website": null,
        "domain": null,
        "language": null,
        "ecosystem": "RedHat",
        "project_tag": "RedHat-HAL",
        "issue_count": 1671
    },
    {
        "id": "SWSQE",
        "name": null,
        "repo": null,
        "website": null,
        "domain": null,
        "language": null,
        "ecosystem": "RedHat",
        "project_tag": "RedHat-SWSQE",
        "issue_count": 1302
    },
    {
        "id": "ISPN",
        "name": null,
        "repo": null,
        "website": null,
        "domain": null,
        "language": null,
        "ecosystem": "RedHat",
        "project_tag": "RedHat-ISPN",
        "issue_count": 13628
    },
    {
        "id": "RHPAM",
        "name": null,
        "repo": null,
        "website": null,
        "domain": null,
        "language": null,
        "ecosystem": "RedHat",
        "project_tag": "RedHat-RHPAM",
        "issue_count": 3139
    },
    {
        "id": "AEROGEAR",
        "name": null,
        "repo": null,
        "website": null,
        "domain": null,
        "language": null,
        "ecosystem": "RedHat",
        "project_tag": "RedHat-AEROGEAR",
        "issue_count": 9715
    },
    {
        "id": "MODE",
        "name": null,
        "repo": null,
        "website": null,
        "domain": null,
        "language": null,
        "ecosystem": "RedHat",
        "project_tag": "RedHat-MODE",
        "issue_count": 2680
    },
    {
        "id": "SWITCHYARD",
        "name": null,
        "repo": null,
        "website": null,
        "domain": null,
        "language": null,
        "ecosystem": "RedHat",
        "project_tag": "RedHat-SWITCHYARD",
        "issue_count": 3015
    },
    {
        "id": "RHODS",
        "name": null,
        "repo": null,
        "website": null,
        "domain": null,
        "language": null,
        "ecosystem": "RedHat",
        "project_tag": "RedHat-RHODS",
        "issue_count": 4820
    },
    {
        "id": "RESTEASY",
        "name": null,
        "repo": null,
        "website": null,
        "domain": null,
        "language": null,
        "ecosystem": "RedHat",
        "project_tag": "RedHat-RESTEASY",
        "issue_count": 3133
    },
    {
        "id": "BXMSDOC",
        "name": null,
        "repo": null,
        "website": null,
        "domain": null,
        "language": null,
        "ecosystem": "RedHat",
        "project_tag": "RedHat-BXMSDOC",
        "issue_count": 3818
    },
    {
        "name": "Windup",
        "id": "WINDUP",
        "repo": "https://github.com/windup",
        "website": "https://developers.redhat.com/products/rhamt/overview/",
        "domain": "Middleware",
        "language": null,
        "ecosystem": "RedHat",
        "project_tag": "RedHat-WINDUP",
        "issue_count": 3455
    },
    {
        "id": "RHBRMS",
        "name": null,
        "repo": null,
        "website": null,
        "domain": null,
        "language": null,
        "ecosystem": "RedHat",
        "project_tag": "RedHat-RHBRMS",
        "issue_count": 2402
    },
    {
        "id": "GITOPS",
        "name": null,
        "repo": null,
        "website": null,
        "domain": null,
        "language": null,
        "ecosystem": "RedHat",
        "project_tag": "RedHat-GITOPS",
        "issue_count": 1154
    },
    {
        "id": "JBSEAM",
        "name": null,
        "repo": null,
        "website": null,
        "domain": null,
        "language": null,
        "ecosystem": "RedHat",
        "project_tag": "RedHat-JBSEAM",
        "issue_count": 5032
    },
    {
        "id": "CEQ",
        "name": null,
        "repo": null,
        "website": null,
        "domain": null,
        "language": null,
        "ecosystem": "RedHat",
        "project_tag": "RedHat-CEQ",
        "issue_count": 1944
    },
    {
        "id": "AF",
        "name": null,
        "repo": null,
        "website": null,
        "domain": null,
        "language": null,
        "ecosystem": "RedHat",
        "project_tag": "RedHat-AF",
        "issue_count": 2712
    },
    {
        "id": "THORN",
        "name": null,
        "repo": null,
        "website": null,
        "domain": null,
        "language": null,
        "ecosystem": "RedHat",
        "project_tag": "RedHat-THORN",
        "issue_count": 2467
    },
    {
        "id": "SOA",
        "name": null,
        "repo": null,
        "website": null,
        "domain": null,
        "language": null,
        "ecosystem": "RedHat",
        "project_tag": "RedHat-SOA",
        "issue_count": 3116
    },
    {
        "id": "KOGITO",
        "name": null,
        "repo": null,
        "website": null,
        "domain": null,
        "language": null,
        "ecosystem": "RedHat",
        "project_tag": "RedHat-KOGITO",
        "issue_count": 8590
    },
    {
        "id": "ENTMQMAAS",
        "name": null,
        "repo": null,
        "website": null,
        "domain": null,
        "language": null,
        "ecosystem": "RedHat",
        "project_tag": "RedHat-ENTMQMAAS",
        "issue_count": 2257
    },
    {
        "id": "RHDM",
        "name": null,
        "repo": null,
        "website": null,
        "domain": null,
        "language": null,
        "ecosystem": "RedHat",
        "project_tag": "RedHat-RHDM",
        "issue_count": 1294
    },
    {
        "id": "JBDS",
        "name": null,
        "repo": null,
        "website": null,
        "domain": null,
        "language": null,
        "ecosystem": "RedHat",
        "project_tag": "RedHat-JBDS",
        "issue_count": 4226
    },
    {
        "id": "JBPAPP",
        "name": null,
        "repo": null,
        "website": null,
        "domain": null,
        "language": null,
        "ecosystem": "RedHat",
        "project_tag": "RedHat-JBPAPP",
        "issue_count": 5933
    },
    {
        "id": "OCPBUGS",
        "name": null,
        "repo": null,
        "website": null,
        "domain": null,
        "language": null,
        "ecosystem": "RedHat",
        "project_tag": "RedHat-OCPBUGS",
        "issue_count": 5622
    },
    {
        "id": "SB",
        "name": null,
        "repo": null,
        "website": null,
        "domain": null,
        "language": null,
        "ecosystem": "RedHat",
        "project_tag": "RedHat-SB",
        "issue_count": 1320
    },
    {
        "id": "JBESB",
        "name": null,
        "repo": null,
        "website": null,
        "domain": null,
        "language": null,
        "ecosystem": "RedHat",
        "project_tag": "RedHat-JBESB",
        "issue_count": 3890
    },
    {
        "name": "JBoss Tools",
        "id": "JBIDE",
        "repo": "https://github.com/jbosstools",
        "website": "https://tools.jboss.org/",
        "domain": "Development",
        "language": null,
        "ecosystem": "RedHat",
        "project_tag": "RedHat-JBIDE",
        "issue_count": 27807
    },
    {
        "id": "JBTM",
        "name": null,
        "repo": null,
        "website": null,
        "domain": null,
        "language": null,
        "ecosystem": "RedHat",
        "project_tag": "RedHat-JBTM",
        "issue_count": 3668
    },
    {
        "id": "JWS",
        "name": null,
        "repo": null,
        "website": null,
        "domain": null,
        "language": null,
        "ecosystem": "RedHat",
        "project_tag": "RedHat-JWS",
        "issue_count": 1042
    },
    {
        "id": "CS",
        "name": null,
        "repo": null,
        "website": null,
        "domain": null,
        "language": null,
        "ecosystem": "RedHat",
        "project_tag": "RedHat-CS",
        "issue_count": 1193
    },
    {
        "id": "JBAS",
        "name": null,
        "repo": null,
        "website": null,
        "domain": null,
        "language": null,
        "ecosystem": "RedHat",
        "project_tag": "RedHat-JBAS",
        "issue_count": 8394
    },
    {
        "id": "OCPPLAN",
        "name": null,
        "repo": null,
        "website": null,
        "domain": null,
        "language": null,
        "ecosystem": "RedHat",
        "project_tag": "RedHat-OCPPLAN",
        "issue_count": 1355
    },
    {
        "id": "MON",
        "name": null,
        "repo": null,
        "website": null,
        "domain": null,
        "language": null,
        "ecosystem": "RedHat",
        "project_tag": "RedHat-MON",
        "issue_count": 1369
    },
    {
        "id": "JBEAP",
        "name": null,
        "repo": null,
        "website": null,
        "domain": null,
        "language": null,
        "ecosystem": "RedHat",
        "project_tag": "RedHat-JBEAP",
        "issue_count": 18048
    },
    {
        "id": "ORG",
        "name": null,
        "repo": null,
        "website": null,
        "domain": null,
        "language": null,
        "ecosystem": "RedHat",
        "project_tag": "RedHat-ORG",
        "issue_count": 1858
    },
    {
        "id": "WELD",
        "name": null,
        "repo": null,
        "website": null,
        "domain": null,
        "language": null,
        "ecosystem": "RedHat",
        "project_tag": "RedHat-WELD",
        "issue_count": 2615
    },
    {
        "id": "OSSM",
        "name": null,
        "repo": null,
        "website": null,
        "domain": null,
        "language": null,
        "ecosystem": "RedHat",
        "project_tag": "RedHat-OSSM",
        "issue_count": 2240
    },
    {
        "id": "FH",
        "name": null,
        "repo": null,
        "website": null,
        "domain": null,
        "language": null,
        "ecosystem": "RedHat",
        "project_tag": "RedHat-FH",
        "issue_count": 2235
    },
    {
        "id": "RFE",
        "name": null,
        "repo": null,
        "website": null,
        "domain": null,
        "language": null,
        "ecosystem": "RedHat",
        "project_tag": "RedHat-RFE",
        "issue_count": 1617
    },
    {
        "id": "JBRULES",
        "name": null,
        "repo": null,
        "website": null,
        "domain": null,
        "language": null,
        "ecosystem": "RedHat",
        "project_tag": "RedHat-JBRULES",
        "issue_count": 3056
    },
    {
        "id": "QUARKUS",
        "name": null,
        "repo": null,
        "website": null,
        "domain": null,
        "language": null,
        "ecosystem": "RedHat",
        "project_tag": "RedHat-QUARKUS",
        "issue_count": 1587
    },
    {
        "id": "ENTESB",
        "name": null,
        "repo": null,
        "website": null,
        "domain": null,
        "language": null,
        "ecosystem": "RedHat",
        "project_tag": "RedHat-ENTESB",
        "issue_count": 14750
    },
    {
        "id": "FUSETOOLS",
        "name": null,
        "repo": null,
        "website": null,
        "domain": null,
        "language": null,
        "ecosystem": "RedHat",
        "project_tag": "RedHat-FUSETOOLS",
        "issue_count": 3431
    },
    {
        "id": "KEYCLOAK",
        "name": null,
        "repo": null,
        "website": null,
        "domain": null,
        "language": null,
        "ecosystem": "RedHat",
        "project_tag": "RedHat-KEYCLOAK",
        "issue_count": 15585
    },
    {
        "id": "AA",
        "name": null,
        "repo": null,
        "website": null,
        "domain": null,
        "language": null,
        "ecosystem": "RedHat",
        "project_tag": "RedHat-AA",
        "issue_count": 1135
    },
    {
        "id": "AAH",
        "name": null,
        "repo": null,
        "website": null,
        "domain": null,
        "language": null,
        "ecosystem": "RedHat",
        "project_tag": "RedHat-AAH",
        "issue_count": 1675
    },
    {
        "id": "LOG",
        "name": null,
        "repo": null,
        "website": null,
        "domain": null,
        "language": null,
        "ecosystem": "RedHat",
        "project_tag": "RedHat-LOG",
        "issue_count": 1938
    },
    {
        "name": "apiman",
        "id": "APIMAN",
        "repo": "https://github.com/apiman",
        "website": "https://www.apiman.io/",
        "domain": "Middleware",
        "language": null,
        "ecosystem": "RedHat",
        "project_tag": "RedHat-APIMAN",
        "issue_count": 1336
    },
    {
        "id": "KATA",
        "name": null,
        "repo": null,
        "website": null,
        "domain": null,
        "language": null,
        "ecosystem": "RedHat",
        "project_tag": "RedHat-KATA",
        "issue_count": 1125
    },
    {
        "id": "OPECO",
        "name": null,
        "repo": null,
        "website": null,
        "domain": null,
        "language": null,
        "ecosystem": "RedHat",
        "project_tag": "RedHat-OPECO",
        "issue_count": 1082
    },
    {
        "id": "EJBTHREE",
        "name": null,
        "repo": null,
        "website": null,
        "domain": null,
        "language": null,
        "ecosystem": "RedHat",
        "project_tag": "RedHat-EJBTHREE",
        "issue_count": 2190
    },
    {
        "id": "DESIGN",
        "name": null,
        "repo": null,
        "website": null,
        "domain": null,
        "language": null,
        "ecosystem": "RedHat",
        "project_tag": "RedHat-DESIGN",
        "issue_count": 1862
    },
    {
        "id": "RHSSO",
        "name": null,
        "repo": null,
        "website": null,
        "domain": null,
        "language": null,
        "ecosystem": "RedHat",
        "project_tag": "RedHat-RHSSO",
        "issue_count": 1680
    },
    {
        "id": "SDN",
        "name": null,
        "repo": null,
        "website": null,
        "domain": null,
        "language": null,
        "ecosystem": "RedHat",
        "project_tag": "RedHat-SDN",
        "issue_count": 1561
    },
    {
        "id": "ENTMQBR",
        "name": null,
        "repo": null,
        "website": null,
        "domain": null,
        "language": null,
        "ecosystem": "RedHat",
        "project_tag": "RedHat-ENTMQBR",
        "issue_count": 4572
    },
    {
        "id": "SRVKP",
        "name": null,
        "repo": null,
        "website": null,
        "domain": null,
        "language": null,
        "ecosystem": "RedHat",
        "project_tag": "RedHat-SRVKP",
        "issue_count": 1470
    },
    {
        "id": "MGDSTRM",
        "name": null,
        "repo": null,
        "website": null,
        "domain": null,
        "language": null,
        "ecosystem": "RedHat",
        "project_tag": "RedHat-MGDSTRM",
        "issue_count": 1973
    },
    {
        "id": "HAWKULAR",
        "name": null,
        "repo": null,
        "website": null,
        "domain": null,
        "language": null,
        "ecosystem": "RedHat",
        "project_tag": "RedHat-HAWKULAR",
        "issue_count": 1309
    },
    {
        "id": "DROOLS",
        "name": null,
        "repo": null,
        "website": null,
        "domain": null,
        "language": null,
        "ecosystem": "RedHat",
        "project_tag": "RedHat-DROOLS",
        "issue_count": 6658
    },
    {
        "id": "COST",
        "name": null,
        "repo": null,
        "website": null,
        "domain": null,
        "language": null,
        "ecosystem": "RedHat",
        "project_tag": "RedHat-COST",
        "issue_count": 2814
    },
    {
        "name": "JGroups",
        "id": "JGRP",
        "repo": "https://github.com/belaban/JGroups",
        "website": "http://jgroups.org",
        "domain": "Operations",
        "language": "Java",
        "ecosystem": "RedHat",
        "project_tag": "RedHat-JGRP",
        "issue_count": 2559
    },
    {
        "name": "Debezium",
        "id": "DBZ",
        "repo": "https://github.com/debezium/",
        "website": "http://debezium.io/",
        "domain": "Middleware",
        "language": null,
        "ecosystem": "RedHat",
        "project_tag": "RedHat-DBZ",
        "issue_count": 5800
    },
    {
        "id": "CLOUD",
        "name": null,
        "repo": null,
        "website": null,
        "domain": null,
        "language": null,
        "ecosystem": "RedHat",
        "project_tag": "RedHat-CLOUD",
        "issue_count": 2311
    },
    {
        "id": "DEVELOPER",
        "name": null,
        "repo": null,
        "website": null,
        "domain": null,
        "language": null,
        "ecosystem": "RedHat",
        "project_tag": "RedHat-DEVELOPER",
        "issue_count": 5435
    },
    {
        "id": "CNV",
        "name": null,
        "repo": null,
        "website": null,
        "domain": null,
        "language": null,
        "ecosystem": "RedHat",
        "project_tag": "RedHat-CNV",
        "issue_count": 2932
    },
    {
        "id": "THREESCALE",
        "name": null,
        "repo": null,
        "website": null,
        "domain": null,
        "language": null,
        "ecosystem": "RedHat",
        "project_tag": "RedHat-THREESCALE",
        "issue_count": 5448
    },
    {
        "id": "ELY",
        "name": null,
        "repo": null,
        "website": null,
        "domain": null,
        "language": null,
        "ecosystem": "RedHat",
        "project_tag": "RedHat-ELY",
        "issue_count": 2342
    },
    {
        "id": "JBPM",
        "name": null,
        "repo": null,
        "website": null,
        "domain": null,
        "language": null,
        "ecosystem": "RedHat",
        "project_tag": "RedHat-JBPM",
        "issue_count": 9240
    },
    {
        "id": "JDG",
        "name": null,
        "repo": null,
        "website": null,
        "domain": null,
        "language": null,
        "ecosystem": "RedHat",
        "project_tag": "RedHat-JDG",
        "issue_count": 1990
    },
    {
        "id": "JBJCA",
        "name": null,
        "repo": null,
        "website": null,
        "domain": null,
        "language": null,
        "ecosystem": "RedHat",
        "project_tag": "RedHat-JBJCA",
        "issue_count": 1425
    },
    {
        "id": "WFLY",
        "name": null,
        "repo": null,
        "website": null,
        "domain": null,
        "language": null,
        "ecosystem": "RedHat",
        "project_tag": "RedHat-WFLY",
        "issue_count": 14646
    },
    {
        "id": "PROJQUAY",
        "name": null,
        "repo": null,
        "website": null,
        "domain": null,
        "language": null,
        "ecosystem": "RedHat",
        "project_tag": "RedHat-PROJQUAY",
        "issue_count": 4018
    },
    {
        "name": "Arquillian",
        "id": "ARQ",
        "repo": "https://github.com/arquillian",
        "website": "http://arquillian.org",
        "domain": "Middleware",
        "language": null,
        "ecosystem": "RedHat",
        "project_tag": "RedHat-ARQ",
        "issue_count": 2175
    },
    {
        "id": "CONSOLE",
        "name": null,
        "repo": null,
        "website": null,
        "domain": null,
        "language": null,
        "ecosystem": "RedHat",
        "project_tag": "RedHat-CONSOLE",
        "issue_count": 1050
    },
    {
        "id": "ENTMQST",
        "name": null,
        "repo": null,
        "website": null,
        "domain": null,
        "language": null,
        "ecosystem": "RedHat",
        "project_tag": "RedHat-ENTMQST",
        "issue_count": 3141
    },
    {
        "name": "JBoss Forge",
        "id": "FORGE",
        "repo": "https://github.com/forge",
        "website": "http://forge.jboss.org",
        "domain": "Middleware",
        "language": null,
        "ecosystem": "RedHat",
        "project_tag": "RedHat-FORGE",
        "issue_count": 2636
    },
    {
        "id": "AS7",
        "name": null,
        "repo": null,
        "website": null,
        "domain": null,
        "language": null,
        "ecosystem": "RedHat",
        "project_tag": "RedHat-AS7",
        "issue_count": 5427
    },
    {
        "id": "TEIID",
        "name": null,
        "repo": null,
        "website": null,
        "domain": null,
        "language": null,
        "ecosystem": "RedHat",
        "project_tag": "RedHat-TEIID",
        "issue_count": 5775
    },
    {
        "id": "PLANNER",
        "name": null,
        "repo": null,
        "website": null,
        "domain": null,
        "language": null,
        "ecosystem": "RedHat",
        "project_tag": "RedHat-PLANNER",
        "issue_count": 2827
    },
    {
        "id": "ENTMQ",
        "name": null,
        "repo": null,
        "website": null,
        "domain": null,
        "language": null,
        "ecosystem": "RedHat",
        "project_tag": "RedHat-ENTMQ",
        "issue_count": 1480
    },
    {
        "id": "RHCLOUD",
        "name": null,
        "repo": null,
        "website": null,
        "domain": null,
        "language": null,
        "ecosystem": "RedHat",
        "project_tag": "RedHat-RHCLOUD",
        "issue_count": 3959
    }
]